{
    "id": "book",
    "metadata": {
        "operation": "retrieve",
        "provider": "Oxford University Press",
        "schema": "RetrieveEntry"
    },
    "results": [
        {
            "id": "book",
            "language": "en-gb",
            "lexicalEntries": [
                {
                    "entries": [
                        {
                            "senses": [
                                {
                                    "definitions": [
                                        "a written or printed work consisting of pages glued or sewn together along one side and bound in covers"
                                    ],
                                    "id": "m_en_gbus0113460.006",
                                    "subsenses": [
                                        {
                                            "definitions": [
                                                "a literary composition that is published or intended for publication as a book"
                                            ],
                                            "id": "m_en_gbus0113460.009"
                                        },
                                        {
                                            "definitions": [
                                                "a main division of a literary work or of the Bible"
                                            ],
                                            "id": "m_en_gbus0113460.010"
                                        },
                                        {
                                            "definitions": [
                                                "the libretto of a musical or opera, or the script of a play."
                                            ],
                                            "id": "m_en_gbus0113460.011"
                                        },
                                        {
                                            "definitions": [
                                                "used to refer to studying"
                                            ],
                                            "id": "m_en_gbus0113460.013"
                                        },
                                        {
                                            "definitions": [
                                                "the phone directory for the area in which someone lives"
                                            ],
                                            "id": "m_en_gbus0113460.015"
                                        },
                                        {
                                            "definitions": [
                                                "a magazine"
                                            ],
                                            "id": "m_en_gbus0113460.018"
                                        },
                                        {
                                            "definitions": [
                                                "an imaginary record or list (often used to emphasize the comprehensiveness of someone's actions or experience)"
                                            ],
                                            "id": "m_en_gbus0113460.019"
                                        }
                                    ]
                                },
                                {
                                    "definitions": [
                                        "a bound set of blank sheets for writing in"
                                    ],
                                    "id": "m_en_gbus0113460.021",
                                    "subsenses": [
                                        {
                                            "definitions": [
                                                "a set of records or accounts"
                                            ],
                                            "id": "m_en_gbus0113460.022"
                                        },
                                        {
                                            "definitions": [
                                                "a bookmaker's record of bets accepted and money paid out."
                                            ],
                                            "id": "m_en_gbus0113460.023"
                                        },
                                        {
                                            "definitions": [
                                                "the notebook in which a referee writes the names of players who are cautioned for foul play"
                                            ],
                                            "id": "m_en_gbus0113460.024"
                                        },
                                        {
                                            "definitions": [
                                                "the first six tricks taken by the declarer in a hand of bridge, after which further tricks count towards fulfilling the contract."
                                            ],
                                            "id": "m_en_gbus0113460.025"
                                        }
                                    ]
                                },
                                {
                                    "definitions": [
                                        "a set of tickets, stamps, matches, samples of cloth, etc., bound together"
                                    ],
                                    "id": "m_en_gbus0113460.027"
                                }
                            ]
                        }
                    ],
                    "language": "en-gb",
                    "lexicalCategory": {
                        "id": "noun",
                        "text": "Noun"
                    },
                    "text": "book"
                },
                {
                    "entries": [
                        {
                            "senses": [
                                {
                                    "definitions": [
                                        "reserve (accommodation, a place, etc.); buy (a ticket) in advance"
                                    ],
                                    "id": "m_en_gbus0113460.030",
                                    "subsenses": [
                                        {
                                            "definitions": [
                                                "reserve accommodation for (someone)"
                                            ],
                                            "id": "m_en_gbus0113460.036"
                                        },
                                        {
                                            "definitions": [
                                                "register one's arrival at a hotel"
                                            ],
                                            "id": "m_en_gbus0113460.037"
                                        },
                                        {
                                            "definitions": [
                                                "engage (a performer or guest) for an event"
                                            ],
                                            "id": "m_en_gbus0113460.038"
                                        },
                                        {
                                            "definitions": [
                                                "have all places reserved; be full"
                                            ],
                                            "id": "m_en_gbus0113460.039"
                                        }
                                    ]
                                },
                                {
                                    "definitions": [
                                        "make an official note of the personal details of (a person who has broken a law or rule)"
                                    ],
                                    "id": "m_en_gbus0113460.041",
                                    "subsenses": [
                                        {
                                            "definitions": [
                                                "(of a referee) note down the name of (a player) who is cautioned for foul play"
                                            ],
                                            "id": "m_en_gbus0113460.042"
                                        }
                                    ]
                                },
                                {
                                    "definitions": [
                                        "leave suddenly"
                                    ],
                                    "id": "m_en_gbus0113460.044",
                                    "subsenses": [
                                        {
                                            "definitions": [
                                                "move quickly; hurry"
                                            ],
                                            "id": "m_en_gbus0113460.045"
                                        }
                                    ]
                                }
                            ]
                        }
                    ],
                    "language": "en-gb",
                    "lexicalCategory": {
                        "id": "verb",
                        "text": "Verb"
                    },
                    "text": "book"
                }
            ],
            "type": "headword",
            "word": "book"
        }
    ],
    "word": "book"
}